MANIFEST.in
README.md
requirements.dev.txt
requirements.txt
setup.py
pysimulator/__init__.py
pysimulator/exec.py
pysimulator/version.py
pysimulator.egg-info/PKG-INFO
pysimulator.egg-info/SOURCES.txt
pysimulator.egg-info/dependency_links.txt
pysimulator.egg-info/not-zip-safe
pysimulator.egg-info/requires.txt
pysimulator.egg-info/top_level.txt
pysimulator/protocols/__init__.py
pysimulator/protocols/device.py
pysimulator/protocols/runtime.py
pysimulator/protocols/commands/__init__.py
pysimulator/protocols/commands/list.py