Metadata-Version: 2.1
Name: pysimulator
Version: 0.1.0
Summary: UNKNOWN
Home-page: https://github.com/youngfeeFJS/pysimulator.git
Author: youngfreeFJS
License: UNKNOWN
Platform: UNKNOWN
Classifier: Programming Language :: Python :: 3 :: Only
Classifier: Programming Language :: Python :: 3.7
Classifier: Programming Language :: Python :: 3.8
Classifier: Programming Language :: Python :: 3.9
Classifier: Programming Language :: Python :: 3.10
Classifier: Programming Language :: Python :: 3.11
Classifier: Operating System :: MacOS
Provides-Extra: dev
